<?xml version="1.0" encoding="ISO-8859-1"?>
<root>
	<item id="Title"><![CDATA[Discuz! Plugin]]></item>
	<item id="Version"><![CDATA[X3.4]]></item>
	<item id="Time"><![CDATA[2017-12-20 19:23]]></item>
	<item id="From"><![CDATA[Discuz! Board (http://bbs.liangjianyun.com/)]]></item>
	<item id="Data">
		<item id="plugin">
			<item id="available"><![CDATA[1]]></item>
			<item id="adminid"><![CDATA[1]]></item>
			<item id="name"><![CDATA[關閉PC電腦端(二維碼)]]></item>
			<item id="identifier"><![CDATA[closepc]]></item>
			<item id="description"><![CDATA[]]></item>
			<item id="datatables"><![CDATA[]]></item>
			<item id="directory"><![CDATA[closepc/]]></item>
			<item id="copyright"><![CDATA[亮劍雲(http://www.liangjianyun.com/)]]></item>
			<item id="version"><![CDATA[2.1.1]]></item>
			<item id="__modules">
				<item id="0">
					<item id="name"><![CDATA[hook]]></item>
					<item id="param"><![CDATA[]]></item>
					<item id="menu"><![CDATA[]]></item>
					<item id="url"><![CDATA[]]></item>
					<item id="type"><![CDATA[11]]></item>
					<item id="adminid"><![CDATA[0]]></item>
					<item id="displayorder"><![CDATA[0]]></item>
					<item id="navtitle"><![CDATA[]]></item>
					<item id="navicon"><![CDATA[]]></item>
					<item id="navsubname"><![CDATA[]]></item>
					<item id="navsuburl"><![CDATA[]]></item>
				</item>
				<item id="1">
					<item id="name"><![CDATA[hook]]></item>
					<item id="param"><![CDATA[]]></item>
					<item id="menu"><![CDATA[]]></item>
					<item id="url"><![CDATA[]]></item>
					<item id="type"><![CDATA[28]]></item>
					<item id="adminid"><![CDATA[0]]></item>
					<item id="displayorder"><![CDATA[0]]></item>
					<item id="navtitle"><![CDATA[]]></item>
					<item id="navicon"><![CDATA[]]></item>
					<item id="navsubname"><![CDATA[]]></item>
					<item id="navsuburl"><![CDATA[]]></item>
				</item>
				<item id="2">
					<item id="name"><![CDATA[app]]></item>
					<item id="param"><![CDATA[]]></item>
					<item id="menu"><![CDATA[更多亮劍應用]]></item>
					<item id="url"><![CDATA[]]></item>
					<item id="type"><![CDATA[3]]></item>
					<item id="adminid"><![CDATA[0]]></item>
					<item id="displayorder"><![CDATA[0]]></item>
					<item id="navtitle"><![CDATA[]]></item>
					<item id="navicon"><![CDATA[]]></item>
					<item id="navsubname"><![CDATA[]]></item>
					<item id="navsuburl"><![CDATA[]]></item>
				</item>
			</item>
		</item>
		<item id="version"><![CDATA[X2.5,X3,X3.1,X3.2,X3.3,X3.4,F1.0,L1.0]]></item>
		<item id="var">
			<item id="0">
				<item id="displayorder"><![CDATA[6]]></item>
				<item id="title"><![CDATA[管理員特權]]></item>
				<item id="description"><![CDATA[開啟後管理員將可以正常打開PC端站點， 其他用戶訪問PC端將還是只顯示二維碼]]></item>
				<item id="variable"><![CDATA[is_admin]]></item>
				<item id="type"><![CDATA[radio]]></item>
				<item id="value"><![CDATA[1]]></item>
				<item id="extra"><![CDATA[]]></item>
			</item>
			<item id="1">
				<item id="displayorder"><![CDATA[8]]></item>
				<item id="title"><![CDATA[二維碼路徑]]></item>
				<item id="description"><![CDATA[]]></item>
				<item id="variable"><![CDATA[path]]></item>
				<item id="type"><![CDATA[text]]></item>
				<item id="value"><![CDATA[http://liangjianyun.oss-cn-shanghai.aliyuncs.com/getqrcode.jpeg]]></item>
				<item id="extra"><![CDATA[]]></item>
			</item>
			<item id="2">
				<item id="displayorder"><![CDATA[10]]></item>
				<item id="title"><![CDATA[二維碼標題]]></item>
				<item id="description"><![CDATA[]]></item>
				<item id="variable"><![CDATA[title]]></item>
				<item id="type"><![CDATA[text]]></item>
				<item id="value"><![CDATA[亮劍雲創新社群]]></item>
				<item id="extra"><![CDATA[]]></item>
			</item>
			<item id="3">
				<item id="displayorder"><![CDATA[12]]></item>
				<item id="title"><![CDATA[二維碼描述]]></item>
				<item id="description"><![CDATA[]]></item>
				<item id="variable"><![CDATA[description]]></item>
				<item id="type"><![CDATA[textarea]]></item>
				<item id="value"><![CDATA[心懷誠信，手握誠實，細微處顯精益，產品上見良心]]></item>
				<item id="extra"><![CDATA[]]></item>
			</item>
			<item id="4">
				<item id="displayorder"><![CDATA[22]]></item>
				<item id="title"><![CDATA[SEO-標題]]></item>
				<item id="description"><![CDATA[]]></item>
				<item id="variable"><![CDATA[seo_title]]></item>
				<item id="type"><![CDATA[text]]></item>
				<item id="value"><![CDATA[亮劍雲]]></item>
				<item id="extra"><![CDATA[]]></item>
			</item>
			<item id="5">
				<item id="displayorder"><![CDATA[24]]></item>
				<item id="title"><![CDATA[SEO-描述]]></item>
				<item id="description"><![CDATA[]]></item>
				<item id="variable"><![CDATA[seo_description]]></item>
				<item id="type"><![CDATA[textarea]]></item>
				<item id="value"><![CDATA[亮劍雲]]></item>
				<item id="extra"><![CDATA[]]></item>
			</item>
			<item id="6">
				<item id="displayorder"><![CDATA[28]]></item>
				<item id="title"><![CDATA[防屏蔽鏈接關鍵詞]]></item>
				<item id="description"><![CDATA[一行一個，模糊匹配]]></item>
				<item id="variable"><![CDATA[keys]]></item>
				<item id="type"><![CDATA[textarea]]></item>
				<item id="value"><![CDATA[plugin]]></item>
				<item id="extra"><![CDATA[]]></item>
			</item>
		</item>
	</item>
</root>